haystack_integrations/document_stores/duckdb/__init__.py
haystack_integrations/document_stores/duckdb/_version.py
haystack_integrations/document_stores/duckdb/document_store.py
haystack_integrations/document_stores/duckdb/py.typed
haystack_integrations/document_stores/duckdb/utils.py
haystack_integrations/retrievers/duckdb/__init__.py
haystack_integrations/retrievers/duckdb/py.typed
haystack_integrations/retrievers/duckdb/retriever.py
duckdb_haystack-0.0.1.post1.dist-info/METADATA
duckdb_haystack-0.0.1.post1.dist-info/WHEEL
duckdb_haystack-0.0.1.post1.dist-info/licenses/LICENSE
duckdb_haystack-0.0.1.post1.dist-info/RECORD
