Metadata-Version: 2.4
Name: duckdb-haystack
Version: 0.0.1.post1
Summary: Haystack document store and retriever for DuckDB VSS
Project-URL: Documentation, https://github.com/AdrianoKF/duckdb-haystack#readme
Project-URL: Issues, https://github.com/AdrianoKF/duckdb-haystack/issues
Project-URL: Source, https://github.com/AdrianoKF/duckdb-haystack
Author-email: Adrian Rumpold <a.rumpold@gmail.com>
License-Expression: Apache-2.0
License-File: LICENSE
Keywords: DuckDB,haystack-ai
Classifier: Development Status :: 4 - Beta
Classifier: Programming Language :: Python
Classifier: Programming Language :: Python :: 3.10
Classifier: Programming Language :: Python :: 3.11
Classifier: Programming Language :: Python :: 3.12
Classifier: Programming Language :: Python :: 3.13
Classifier: Programming Language :: Python :: 3.14
Classifier: Programming Language :: Python :: Implementation :: CPython
Requires-Python: >=3.10
Requires-Dist: duckdb>=0.10.3
Requires-Dist: haystack-ai
Requires-Dist: pandas>=2.3.3
Requires-Dist: typing-extensions
